tplconfig/__init__.py
tplconfig/config_from.py
tplconfig/jinja_config.py
tplconfig/runner.py
tplconfig/utils.py
tplconfig/version.py
tplconfig/tests/__init__.py
tplconfig/tests/test_config_class.py
tplconfig/tests/test_template.py
tplconfig/tests/test_yaml.py
tplconfig/tests/resources/__init__.py
tplconfig/tests/resources/badvalue.tpl
tplconfig/tests/resources/config.conf.tpl
tplconfig/tests/resources/config.yml
tplconfig/tests/resources/dummy.py
tplconfig/tests/resources/templates_package/__init__.py
tplconfig/tests/resources/templates_package/templates/config.conf.tpl
tplconfig-0.1.0.dist-info/DESCRIPTION.rst
tplconfig-0.1.0.dist-info/METADATA
tplconfig-0.1.0.dist-info/RECORD
tplconfig-0.1.0.dist-info/WHEEL
tplconfig-0.1.0.dist-info/entry_points.txt
tplconfig-0.1.0.dist-info/metadata.json
tplconfig-0.1.0.dist-info/top_level.txt
