Metadata-Version: 2.0
Name: tplconfig
Version: 0.1.0
Summary: Configuration with jinja templates
Home-page: https://github.com/srault95/tplconfig
Author: Stéphane RAULT
Author-email: stephane.rault@radicalspam.org
License: BSD
Keywords: jinja2,template,devops
Platform: UNKNOWN
Classifier: Development Status :: 4 - Beta
Classifier: Topic :: Software Development
Classifier: Topic :: Utilities
Classifier: Operating System :: OS Independent
Classifier: Programming Language :: Python
Classifier: Programming Language :: Python :: 2
Classifier: Programming Language :: Python :: 2.7
Classifier: Programming Language :: Python :: 3.4
Classifier: Programming Language :: Python :: 3.5
Classifier: License :: OSI Approved :: BSD License
Classifier: Intended Audience :: Developers
Classifier: Intended Audience :: System Administrators
Requires-Dist: PyYAML
Requires-Dist: jinja2
Requires-Dist: requests
Requires-Dist: six
